{"aaf9588de2f3e4cbb94af3ea1eb7e26f:f9f027b7145533ec725ac3e2b45e69d0":{"statistic":{"failed":0,"broken":0,"skipped":0,"passed":1,"unknown":0,"total":1},"items":[{"uid":"e6b7cdc20d82d2a","reportUrl":"https://serhatgemici.github.io/playwright-bdd-boilerplate/18/#testresult/e6b7cdc20d82d2a","status":"passed","time":{"start":1781185318428,"stop":1781185327538,"duration":9110}}]},"7c4d777bcadc3c685c8ebef3eeadae91:f9f027b7145533ec725ac3e2b45e69d0":{"statistic":{"failed":0,"broken":0,"skipped":0,"passed":1,"unknown":0,"total":1},"items":[{"uid":"d691e84993f521f4","reportUrl":"https://serhatgemici.github.io/playwright-bdd-boilerplate/18/#testresult/d691e84993f521f4","status":"passed","time":{"start":1781185318541,"stop":1781185324563,"duration":6022}}]},"a8e88f2ea033139dec7571b89e303ec3:f9f027b7145533ec725ac3e2b45e69d0":{"statistic":{"failed":1,"broken":0,"skipped":0,"passed":0,"unknown":0,"total":1},"items":[{"uid":"3450f49ef4d73ebd","reportUrl":"https://serhatgemici.github.io/playwright-bdd-boilerplate/18/#testresult/3450f49ef4d73ebd","status":"failed","statusDetails":"Error: locator.click: Error: strict mode violation: getByRole('radio', { name: 'Mr' }) resolved to 2 elements:\n    1) <input value=\"Mr\" type=\"radio\" name=\"title\" id=\"id_gender1\"/> aka getByRole('radio', { name: 'Mr.' })\n    2) <input value=\"Mrs\" type=\"radio\" name=\"title\" id=\"id_gender2\"/> aka getByRole('radio', { name: 'Mrs.' })\n\nCall log:\n  - waiting for getByRole('radio', { name: 'Mr' })\n","time":{"start":1781185331230,"stop":1781185337498,"duration":6268}}]},"b431f91e18d10a154c024869de42ca0e:f9f027b7145533ec725ac3e2b45e69d0":{"statistic":{"failed":0,"broken":0,"skipped":0,"passed":1,"unknown":0,"total":1},"items":[{"uid":"cc233874de44d071","reportUrl":"https://serhatgemici.github.io/playwright-bdd-boilerplate/18/#testresult/cc233874de44d071","status":"passed","time":{"start":1781185307762,"stop":1781185318892,"duration":11130}}]},"459b4bf52474b2f37c542de29d37ef66:f9f027b7145533ec725ac3e2b45e69d0":{"statistic":{"failed":0,"broken":0,"skipped":0,"passed":1,"unknown":0,"total":1},"items":[{"uid":"90a3f735aad945a3","reportUrl":"https://serhatgemici.github.io/playwright-bdd-boilerplate/18/#testresult/90a3f735aad945a3","status":"passed","time":{"start":1781185307391,"stop":1781185317886,"duration":10495}}]},"46347ee0919c5103e3b11d315afcd082:f9f027b7145533ec725ac3e2b45e69d0":{"statistic":{"failed":0,"broken":0,"skipped":0,"passed":1,"unknown":0,"total":1},"items":[{"uid":"8e3ac3542820d0af","reportUrl":"https://serhatgemici.github.io/playwright-bdd-boilerplate/18/#testresult/8e3ac3542820d0af","status":"passed","time":{"start":1781185307691,"stop":1781185317898,"duration":10207}}]}}